coord2region/__init__.py
coord2region/_version.py
coord2region/ai_helpers.py
coord2region/ai_model_interface.py
coord2region/ai_reports.py
coord2region/cli.py
coord2region/config.py
coord2region/coord2region.py
coord2region/coord2study.py
coord2region/fetching.py
coord2region/llm.py
coord2region/paths.py
coord2region/pipeline.py
coord2region/utils/__init__.py
coord2region/utils/file_handler.py
coord2region/utils/image_utils.py
coord2region/utils/paths.py
coord2region/utils/utils.py
coord2region-0.1.4.dist-info/licenses/LICENSE
coord2region-0.1.4.dist-info/METADATA
coord2region-0.1.4.dist-info/WHEEL
coord2region-0.1.4.dist-info/entry_points.txt
coord2region-0.1.4.dist-info/top_level.txt
coord2region-0.1.4.dist-info/RECORD
