Metadata-Version: 2.4
Name: coord2region
Version: 0.1.4
Summary: Find region name for a given MNI coordinate in a selected atlas
Author-email: Hamza Abdelhedi <hamza.abdelhedii@gmail.com>
License-Expression: BSD-3-Clause
Project-URL: Homepage, https://github.com/BabaSanfour/Coord2Region
Project-URL: Issues, https://github.com/BabaSanfour/Coord2Region/issues
Classifier: Programming Language :: Python :: 3
Classifier: Operating System :: OS Independent
Requires-Python: <3.14,>=3.10
License-File: LICENSE
Requires-Dist: biopython
Requires-Dist: mne
Requires-Dist: nibabel
Requires-Dist: nilearn==0.12.0
Requires-Dist: nimare==0.4.0
Requires-Dist: numpy
Requires-Dist: pandas
Requires-Dist: pydantic>=2.6.0
Requires-Dist: scipy
Requires-Dist: requests
Requires-Dist: pyyaml
Requires-Dist: openpyxl
Requires-Dist: Pillow
Requires-Dist: fpdf
Requires-Dist: anthropic
Requires-Dist: diffusers
Requires-Dist: google-genai
Requires-Dist: openai>=1.0.0
Requires-Dist: transformers
Requires-Dist: pooch>=1.5
Provides-Extra: dev
Requires-Dist: pre-commit; extra == "dev"
Requires-Dist: pytest-cov; extra == "dev"
Requires-Dist: ruff; extra == "dev"
Requires-Dist: torch>=2.0.0; extra == "dev"
Provides-Extra: docs
Requires-Dist: insegel; extra == "docs"
Requires-Dist: myst-parser; extra == "docs"
Requires-Dist: pydata-sphinx-theme; extra == "docs"
Requires-Dist: packaging; extra == "docs"
Requires-Dist: sphinx>=4.0.0; extra == "docs"
Requires-Dist: sphinx-autoapi; extra == "docs"
Requires-Dist: sphinx-copybutton; extra == "docs"
Requires-Dist: sphinx-gallery; extra == "docs"
Requires-Dist: sphinxcontrib-mermaid; extra == "docs"
Dynamic: license-file
